Workbook

Sheet Overview
A1: Task 6 – Excel & Functions Fundamentals
A3: Intern | B3: Rathod Harshvardhansinh J
A4: Track | B4: Data Analytics – Veda Technology Internship
A5: Dataset | B5: Synthetic Superstore-style transactional data (60 orders) – built for practice
A6: Tools | B6: Microsoft Excel / Google Sheets
A8: Sheet | B8: What it shows
A9: Data | B9: 60 transactions: Order ID, Date, Customer, Region, Category, Product ID, Qty, Unit Price, Discount %, Sales
A10: Products | B10: Lookup table (Product ID → name, category, cost)
A11: Lookups | B11: VLOOKUP, INDEX/MATCH, XLOOKUP (documented) incl. exact vs approximate match and error handling
A12: Logic_IF | B12: IF, nested IF, IF + AND/OR, IFERROR
A13: Conditional_Agg | B13: SUMIF, SUMIFS, COUNTIF, COUNTIFS, AVERAGEIFS with named ranges
A14: Text_Functions | B14: LEFT, RIGHT, MID, LEN, TRIM, UPPER/LOWER/PROPER, CONCATENATE/&, SUBSTITUTE, FIND
A15: Edge_Cases | B15: Blank cells, text-vs-number mismatches, trailing spaces, missing lookups
... A18: Note: | B18: Data is synthetic (generated for learning); no real customer data. Change yellow cells to test formulas.

Sheet Products
A1: Product ID | B1: Product Name | C1: Category | D1: Unit Cost
A2: P101 | B2: Office Chair | C2: Furniture | D2: 85
A3: P102 | B3: Standing Desk | C3: Furniture | D3: 210
A4: P103 | B4: Bookcase | C4: Furniture | D4: 60
A5: P201 | B5: Laptop Stand | C5: Technology | D5: 18
A6: P202 | B6: Wireless Mouse | C6: Technology | D6: 9
A7: P203 | B7: Mechanical Keyboard | C7: Technology | D7: 35
A8: P204 | B8: USB-C Hub | C8: Technology | D8: 14
A9: P301 | B9: Notebook Pack | C9: Office Supplies | D9: 4
A10: P302 | B10: Gel Pens (12) | C10: Office Supplies | D10: 3
A11: P303 | B11: Desk Organizer | C11: Office Supplies | D11: 7
A13: Source: sample values created by the intern for practice.

Sheet Data
A1: Order ID | B1: Order Date | C1: Customer | D1: Region | E1: Category | F1: Product ID | G1: Qty | H1: Unit Price | I1: Discount % | J1: Sales | L1: Sales = Qty × Unit Price × (1 − Discount %)
A2: ORD-1001 | B2: 46266 | C2: Isha Desai | D2: East | E2: Technology | F2: P202 | G2: 9 | H2: 14.4 | I2: 0.15 | J2: =G2*H2*(1-I2) -> 110.16 | L2: Synthetic data generated for practice.
A3: ORD-1002 | B3: 46228 | C3: Kabir Joshi | D3: West | E3: Furniture | F3: P102 | G3: 7 | H3: 439.57 | I3: 0.05 | J3: =G3*H3*(1-I3) -> 2923.1405
A4: ORD-1003 | B4: 46250 | C4: Vivek Rao | D4: South | E4: Furniture | F4: P102 | G4: 8 | H4: 439.57 | I4: 0.2 | J4: =G4*H4*(1-I4) -> 2813.248
A5: ORD-1004 | B5: 46229 | C5: Kabir Joshi | D5: West | E5: Furniture | F5: P102 | G5: 1 | H5: 439.57 | I5: 0.15 | J5: =G5*H5*(1-I5) -> 373.6345
A6: ORD-1005 | B6: 46287 | C6: Neha Trivedi | D6: East | E6: Technology | F6: P201 | G6: 4 | H6: 31.63 | I6: 0.15 | J6: =G6*H6*(1-I6) -> 107.542
A7: ORD-1006 | B7: 46286 | C7: Aarav Shah | D7: South | E7: Office Supplies | F7: P303 | G7: 4 | H7: 14.43 | I7: 0.15 | J7: =G7*H7*(1-I7) -> 49.062
A8: ORD-1007 | B8: 46242 | C8: Neha Trivedi | D8: West | E8: Technology | F8: P204 | G8: 2 | H8: 26.35 | I8: 0.15 | J8: =G8*H8*(1-I8) -> 44.795
A9: ORD-1008 | B9: 46229 | C9: Meera Patel | D9: South | E9: Office Supplies | F9: P302 | G9: 5 | H9: 5.47 | I9: 0.2 | J9: =G9*H9*(1-I9) -> 21.88
A10: ORD-1009 | B10: 46252 | C10: Anaya Singh | D10: North | E10: Technology | F10: P201 | G10: 3 | H10: 31.63 | I10: 0.15 | J10: =G10*H10*(1-I10) -> 80.6565
A11: ORD-1010 | B11: 46293 | C11: Aarav Shah | D11: North | E11: Technology | F11: P201 | G11: 3 | H11: 31.63 | I11: 0 | J11: =G11*H11*(1-I11) -> 94.89
A12: ORD-1011 | B12: 46275 | C12: Kabir Joshi | D12: South | E12: Technology | F12: P203 | G12: 7 | H12: 69.92 | I12: 0.15 | J12: =G12*H12*(1-I12) -> 416.024
A13: ORD-1012 | B13: 46241 | C13: Rohan Mehta | D13: East | E13: Technology | F13: P204 | G13: 1 | H13: 26.35 | I13: 0 | J13: =G13*H13*(1-I13) -> 26.35
A14: ORD-1013 | B14: 46280 | C14: Vivek Rao | D14: West | E14: Technology | F14: P204 | G14: 8 | H14: 26.35 | I14: 0 | J14: =G14*H14*(1-I14) -> 210.8
... A61: ORD-1060 | B61: 46292 | C61: Neha Trivedi | D61: East | E61: Technology | F61: P203 | G61: 11 | H61: 69.92 | I61: 0 | J61: =G61*H61*(1-I61) -> 769.12

Sheet Lookups
A1: Lookup Functions
A3: Enter a Product ID (yellow): | B3: P203
A5: Technique | B5: Formula (shown as text) | C5: Result
A6: VLOOKUP – product name (exact) | B6: =VLOOKUP(B3,ProdTable,2,FALSE) | C6: =VLOOKUP(B3,ProdTable,2,FALSE()) -> Mechanical Keyboard
A7: VLOOKUP – category (exact) | B7: =VLOOKUP(B3,ProdTable,3,FALSE) | C7: =VLOOKUP(B3,ProdTable,3,FALSE()) -> Technology
A8: VLOOKUP – unit cost (exact) | B8: =VLOOKUP(B3,ProdTable,4,FALSE) | C8: =VLOOKUP(B3,ProdTable,4,FALSE()) -> 35
A9: INDEX/MATCH – product name | B9: =INDEX(Products!$B$2:$B$11,MATCH(B3,ProdID,0)) | C9: =INDEX(Products!$B$2:$B$11,MATCH(B3,ProdID,0)) -> Mechanical Keyboard
A10: INDEX/MATCH – look LEFT (cost → ID) | B10: =INDEX(Products!$A$2:$A$11,MATCH(9,Products!$D$2:$D$11,0)) | C10: =INDEX(Products!$A$2:$A$11,MATCH(9,Products!$D$2:$D$11,0)) -> P202
A11: XLOOKUP (Excel 365 / Sheets) – name | B11: =XLOOKUP(B3,Products!A2:A11,Products!B2:B11,"Not found") | C11: Excel 365 only – equivalent live result is the INDEX/MATCH row above
A12: VLOOKUP wrapped in IFERROR (missing ID) | B12: =IFERROR(VLOOKUP("P999",ProdTable,2,FALSE),"Not found") | C12: =IFERROR(VLOOKUP("P999",ProdTable,2,FALSE()),"Not found") -> Not found
A15: Approximate-match demo: discount tier by order value
A16: Order value ≥ | B16: Tier
A17: 0 | B17: Bronze
A18: 500 | B18: Silver
A19: 1500 | B19: Gold
A20: 3000 | B20: Platinum
A22: Order value (yellow): | B22: 1820
A23: Tier (VLOOKUP, approximate = TRUE) | B23: =VLOOKUP(B22,A17:B20,2,TRUE()) -> Gold
A24: Approximate match needs the first column sorted ascending.

Sheet Logic_IF
A1: Logic Functions on the Data sheet (first 15 orders)
A3: Order ID | B3: Sales | C3: IF: High / Normal (>=1000) | D3: Nested IF: size band | E3: IF+AND: West & >=800 | F3: IF+OR: Furniture or North | G3: IFERROR: Cost lookup | H3: Profit (Sales − Qty×Cost)
A4: =Data!A2 -> ORD-1001 | B4: =Data!J2 -> 110.16 | C4: =IF(B4>=1000,"High","Normal") -> Normal | D4: =IF(B4>=2000,"Large",IF(B4>=1000,"Medium",IF(B4>=500,"Small","Mini"))) -> Mini | E4: =IF(AND(Data!D2="West",B4>=800),"Yes","No") -> No | F4: =IF(OR(Data!E2="Furniture",Data!D2="North"),"Yes","No") -> No | G4: =IFERROR(VLOOKUP(Data!F2,ProdTable,4,FALSE()),"Missing") -> 9 | H4: =IFERROR(B4-Data!G2*G4,"n/a") -> 29.16
A5: =Data!A3 -> ORD-1002 | B5: =Data!J3 -> 2923.1405 | C5: =IF(B5>=1000,"High","Normal") -> High | D5: =IF(B5>=2000,"Large",IF(B5>=1000,"Medium",IF(B5>=500,"Small","Mini"))) -> Large | E5: =IF(AND(Data!D3="West",B5>=800),"Yes","No") -> Yes | F5: =IF(OR(Data!E3="Furniture",Data!D3="North"),"Yes","No") -> Yes | G5: =IFERROR(VLOOKUP(Data!F3,ProdTable,4,FALSE()),"Missing") -> 210 | H5: =IFERROR(B5-Data!G3*G5,"n/a") -> 1453.1405
A6: =Data!A4 -> ORD-1003 | B6: =Data!J4 -> 2813.248 | C6: =IF(B6>=1000,"High","Normal") -> High | D6: =IF(B6>=2000,"Large",IF(B6>=1000,"Medium",IF(B6>=500,"Small","Mini"))) -> Large | E6: =IF(AND(Data!D4="West",B6>=800),"Yes","No") -> No | F6: =IF(OR(Data!E4="Furniture",Data!D4="North"),"Yes","No") -> Yes | G6: =IFERROR(VLOOKUP(Data!F4,ProdTable,4,FALSE()),"Missing") -> 210 | H6: =IFERROR(B6-Data!G4*G6,"n/a") -> 1133.248
A7: =Data!A5 -> ORD-1004 | B7: =Data!J5 -> 373.6345 | C7: =IF(B7>=1000,"High","Normal") -> Normal | D7: =IF(B7>=2000,"Large",IF(B7>=1000,"Medium",IF(B7>=500,"Small","Mini"))) -> Mini | E7: =IF(AND(Data!D5="West",B7>=800),"Yes","No") -> No | F7: =IF(OR(Data!E5="Furniture",Data!D5="North"),"Yes","No") -> Yes | G7: =IFERROR(VLOOKUP(Data!F5,ProdTable,4,FALSE()),"Missing") -> 210 | H7: =IFERROR(B7-Data!G5*G7,"n/a") -> 163.6345
A8: =Data!A6 -> ORD-1005 | B8: =Data!J6 -> 107.542 | C8: =IF(B8>=1000,"High","Normal") -> Normal | D8: =IF(B8>=2000,"Large",IF(B8>=1000,"Medium",IF(B8>=500,"Small","Mini"))) -> Mini | E8: =IF(AND(Data!D6="West",B8>=800),"Yes","No") -> No | F8: =IF(OR(Data!E6="Furniture",Data!D6="North"),"Yes","No") -> No | G8: =IFERROR(VLOOKUP(Data!F6,ProdTable,4,FALSE()),"Missing") -> 18 | H8: =IFERROR(B8-Data!G6*G8,"n/a") -> 35.542
A9: =Data!A7 -> ORD-1006 | B9: =Data!J7 -> 49.062 | C9: =IF(B9>=1000,"High","Normal") -> Normal | D9: =IF(B9>=2000,"Large",IF(B9>=1000,"Medium",IF(B9>=500,"Small","Mini"))) -> Mini | E9: =IF(AND(Data!D7="West",B9>=800),"Yes","No") -> No | F9: =IF(OR(Data!E7="Furniture",Data!D7="North"),"Yes","No") -> No | G9: =IFERROR(VLOOKUP(Data!F7,ProdTable,4,FALSE()),"Missing") -> 7 | H9: =IFERROR(B9-Data!G7*G9,"n/a") -> 21.062
A10: =Data!A8 -> ORD-1007 | B10: =Data!J8 -> 44.795 | C10: =IF(B10>=1000,"High","Normal") -> Normal | D10: =IF(B10>=2000,"Large",IF(B10>=1000,"Medium",IF(B10>=500,"Small","Mini"))) -> Mini | E10: =IF(AND(Data!D8="West",B10>=800),"Yes","No") -> No | F10: =IF(OR(Data!E8="Furniture",Data!D8="North"),"Yes","No") -> No | G10: =IFERROR(VLOOKUP(Data!F8,ProdTable,4,FALSE()),"Missing") -> 14 | H10: =IFERROR(B10-Data!G8*G10,"n/a") -> 16.795
A11: =Data!A9 -> ORD-1008 | B11: =Data!J9 -> 21.88 | C11: =IF(B11>=1000,"High","Normal") -> Normal | D11: =IF(B11>=2000,"Large",IF(B11>=1000,"Medium",IF(B11>=500,"Small","Mini"))) -> Mini | E11: =IF(AND(Data!D9="West",B11>=800),"Yes","No") -> No | F11: =IF(OR(Data!E9="Furniture",Data!D9="North"),"Yes","No") -> No | G11: =IFERROR(VLOOKUP(Data!F9,ProdTable,4,FALSE()),"Missing") -> 3 | H11: =IFERROR(B11-Data!G9*G11,"n/a") -> 6.88
A12: =Data!A10 -> ORD-1009 | B12: =Data!J10 -> 80.6565 | C12: =IF(B12>=1000,"High","Normal") -> Normal | D12: =IF(B12>=2000,"Large",IF(B12>=1000,"Medium",IF(B12>=500,"Small","Mini"))) -> Mini | E12: =IF(AND(Data!D10="West",B12>=800),"Yes","No") -> No | F12: =IF(OR(Data!E10="Furniture",Data!D10="North"),"Yes","No") -> Yes | G12: =IFERROR(VLOOKUP(Data!F10,ProdTable,4,FALSE()),"Missing") -> 18 | H12: =IFERROR(B12-Data!G10*G12,"n/a") -> 26.6565
A13: =Data!A11 -> ORD-1010 | B13: =Data!J11 -> 94.89 | C13: =IF(B13>=1000,"High","Normal") -> Normal | D13: =IF(B13>=2000,"Large",IF(B13>=1000,"Medium",IF(B13>=500,"Small","Mini"))) -> Mini | E13: =IF(AND(Data!D11="West",B13>=800),"Yes","No") -> No | F13: =IF(OR(Data!E11="Furniture",Data!D11="North"),"Yes","No") -> Yes | G13: =IFERROR(VLOOKUP(Data!F11,ProdTable,4,FALSE()),"Missing") -> 18 | H13: =IFERROR(B13-Data!G11*G13,"n/a") -> 40.89
A14: =Data!A12 -> ORD-1011 | B14: =Data!J12 -> 416.024 | C14: =IF(B14>=1000,"High","Normal") -> Normal | D14: =IF(B14>=2000,"Large",IF(B14>=1000,"Medium",IF(B14>=500,"Small","Mini"))) -> Mini | E14: =IF(AND(Data!D12="West",B14>=800),"Yes","No") -> No | F14: =IF(OR(Data!E12="Furniture",Data!D12="North"),"Yes","No") -> No | G14: =IFERROR(VLOOKUP(Data!F12,ProdTable,4,FALSE()),"Missing") -> 35 | H14: =IFERROR(B14-Data!G12*G14,"n/a") -> 171.024
A15: =Data!A13 -> ORD-1012 | B15: =Data!J13 -> 26.35 | C15: =IF(B15>=1000,"High","Normal") -> Normal | D15: =IF(B15>=2000,"Large",IF(B15>=1000,"Medium",IF(B15>=500,"Small","Mini"))) -> Mini | E15: =IF(AND(Data!D13="West",B15>=800),"Yes","No") -> No | F15: =IF(OR(Data!E13="Furniture",Data!D13="North"),"Yes","No") -> No | G15: =IFERROR(VLOOKUP(Data!F13,ProdTable,4,FALSE()),"Missing") -> 14 | H15: =IFERROR(B15-Data!G13*G15,"n/a") -> 12.35
... A18: =Data!A16 -> ORD-1015 | B18: =Data!J16 -> 59.076 | C18: =IF(B18>=1000,"High","Normal") -> Normal | D18: =IF(B18>=2000,"Large",IF(B18>=1000,"Medium",IF(B18>=500,"Small","Mini"))) -> Mini | E18: =IF(AND(Data!D16="West",B18>=800),"Yes","No") -> No | F18: =IF(OR(Data!E16="Furniture",Data!D16="North"),"Yes","No") -> No | G18: =IFERROR(VLOOKUP(Data!F16,ProdTable,4,FALSE()),"Missing") -> 3 | H18: =IFERROR(B18-Data!G16*G18,"n/a") -> 23.076
A20: Tip: build lookups first, then wrap them in IFERROR, then add IF logic – this keeps nested IFs short.

Sheet Conditional_Agg
A1: SUMIF / SUMIFS / COUNTIF / COUNTIFS / AVERAGEIFS (named ranges)
A3: Region: | B3: West
A4: Category: | B4: Technology
A5: Min Qty: | B5: 5
A7: Question | B7: Formula (text) | C7: Result
A8: Total sales in selected region (SUMIF) | B8: =SUMIF(Region,B3,Sales) | C8: =SUMIF(Region,B3,Sales) -> 7079.9965
A9: Total sales: region AND category (SUMIFS) | B9: =SUMIFS(Sales,Region,B3,Category,B4) | C9: =SUMIFS(Sales,Region,B3,Category,B4) -> 2280.3775
A10: Total sales: region, category, Qty ≥ min (SUMIFS) | B10: =SUMIFS(Sales,Region,B3,Category,B4,Qty,">="&B5) | C10: =SUMIFS(Sales,Region,B3,Category,B4,Qty,">="&B5) -> 2235.5825
A11: Number of orders in region (COUNTIF) | B11: =COUNTIF(Region,B3) | C11: =COUNTIF(Region,B3) -> 15
A12: Number of orders: region AND category (COUNTIFS) | B12: =COUNTIFS(Region,B3,Category,B4) | C12: =COUNTIFS(Region,B3,Category,B4) -> 8
A13: Average sale: region AND category (AVERAGEIFS) | B13: =IFERROR(AVERAGEIFS(Sales,Region,B3,Category,B4),0) | C13: =IFERROR(AVERAGEIFS(Sales,Region,B3,Category,B4),0) -> 285.04719
A14: Orders with Qty above 8 (COUNTIF with operator) | B14: =COUNTIF(Qty,">8") | C14: =COUNTIF(Qty,">8") -> 19
A15: Sales in Jul-2026 (SUMIFS with dates) | B15: =SUMIFS(Sales,OrderDate,">="&DATE(2026,7,1),OrderDate,"<"&DATE(2026,8,1)) | C15: =SUMIFS(Sales,OrderDate,">="&DATE(2026,7,1),OrderDate,"<"&DATE(2026,8,1)) -> 16903.599
A16: Orders from names starting with 'A' (wildcard) | B16: =COUNTIF(Customer,"A*") | C16: =COUNTIF(Customer,"A*") -> 17
A17: Total sales (SUM, for reconciliation) | B17: =SUM(Sales) | C17: =SUM(Sales) -> 49889.933
A19: Regional summary (SUMIFS + COUNTIFS)
A20: Region | B20: Total Sales | C20: Orders | D20: Avg Order
A21: West | B21: =SUMIFS(Sales,Region,A21) -> 7079.9965 | C21: =COUNTIFS(Region,A21) -> 15 | D21: =IFERROR(B21/C21,0) -> 471.99977
A22: North | B22: =SUMIFS(Sales,Region,A22) -> 11270.039 | C22: =COUNTIFS(Region,A22) -> 15 | D22: =IFERROR(B22/C22,0) -> 751.3359
A23: South | B23: =SUMIFS(Sales,Region,A23) -> 14630.087 | C23: =COUNTIFS(Region,A23) -> 13 | D23: =IFERROR(B23/C23,0) -> 1125.3913
A24: East | B24: =SUMIFS(Sales,Region,A24) -> 16909.811 | C24: =COUNTIFS(Region,A24) -> 17 | D24: =IFERROR(B24/C24,0) -> 994.69476
A25: Total | B25: =SUM(B21:B24) -> 49889.933 | C25: =SUM(C21:C24) -> 60 | D25: =IFERROR(B25/C25,0) -> 831.49888
A26: Check: regional total equals SUM(Sales) → | C26: =IF(ROUND(B25-SUM(Sales),2)=0,"OK","MISMATCH") -> OK

Sheet Text_Functions
A1: Text Functions (messy data cleaning)
A3: Raw text (typed) | B3: LEN | C3: TRIM | D3: UPPER | E3: LOWER | F3: PROPER | G3: LEFT 3 | H3: RIGHT 4 | I3: MID(5,3) | J3: SUBSTITUTE '-'→'/' | K3: FIND '-' | L3: Cleaned ID = TRIM+UPPER | M3: Customer & Region (&)
A4: ord-1001 | B4: =LEN(A4) -> 11 | C4: =TRIM(A4) -> ord-1001 | D4: =UPPER(A4) -> ORD-1001 | E4: =LOWER(A4) -> ord-1001 | F4: =PROPER(A4) -> Ord-1001 | G4: =LEFT(TRIM(A4),3) -> ord | H4: =RIGHT(TRIM(A4),4) -> 1001 | I4: =MID(TRIM(A4),5,3) -> 100 | J4: =SUBSTITUTE(TRIM(A4),"-","/") -> ord/1001 | K4: =FIND("-",TRIM(A4)) -> 4 | L4: =UPPER(TRIM(A4)) -> ORD-1001 | M4: =Data!C2&" – "&Data!D2 -> Isha Desai – East
A5: ORD-1002 | B5: =LEN(A5) -> 8 | C5: =TRIM(A5) -> ORD-1002 | D5: =UPPER(A5) -> ORD-1002 | E5: =LOWER(A5) -> ord-1002 | F5: =PROPER(A5) -> Ord-1002 | G5: =LEFT(TRIM(A5),3) -> ORD | H5: =RIGHT(TRIM(A5),4) -> 1002 | I5: =MID(TRIM(A5),5,3) -> 100 | J5: =SUBSTITUTE(TRIM(A5),"-","/") -> ORD/1002 | K5: =FIND("-",TRIM(A5)) -> 4 | L5: =UPPER(TRIM(A5)) -> ORD-1002 | M5: =Data!C3&" – "&Data!D3 -> Kabir Joshi – West
A6: ord-1003 | B6: =LEN(A6) -> 10 | C6: =TRIM(A6) -> ord-1003 | D6: =UPPER(A6) -> ORD-1003 | E6: =LOWER(A6) -> ord-1003 | F6: =PROPER(A6) -> Ord-1003 | G6: =LEFT(TRIM(A6),3) -> ord | H6: =RIGHT(TRIM(A6),4) -> 1003 | I6: =MID(TRIM(A6),5,3) -> 100 | J6: =SUBSTITUTE(TRIM(A6),"-","/") -> ord/1003 | K6: =FIND("-",TRIM(A6)) -> 4 | L6: =UPPER(TRIM(A6)) -> ORD-1003 | M6: =Data!C4&" – "&Data!D4 -> Vivek Rao – South
A7: Ord-1004 | B7: =LEN(A7) -> 10 | C7: =TRIM(A7) -> Ord-1004 | D7: =UPPER(A7) -> ORD-1004 | E7: =LOWER(A7) -> ord-1004 | F7: =PROPER(A7) -> Ord-1004 | G7: =LEFT(TRIM(A7),3) -> Ord | H7: =RIGHT(TRIM(A7),4) -> 1004 | I7: =MID(TRIM(A7),5,3) -> 100 | J7: =SUBSTITUTE(TRIM(A7),"-","/") -> Ord/1004 | K7: =FIND("-",TRIM(A7)) -> 4 | L7: =UPPER(TRIM(A7)) -> ORD-1004 | M7: =Data!C5&" – "&Data!D5 -> Kabir Joshi – West
A8: ord-1005 | B8: =LEN(A8) -> 8 | C8: =TRIM(A8) -> ord-1005 | D8: =UPPER(A8) -> ORD-1005 | E8: =LOWER(A8) -> ord-1005 | F8: =PROPER(A8) -> Ord-1005 | G8: =LEFT(TRIM(A8),3) -> ord | H8: =RIGHT(TRIM(A8),4) -> 1005 | I8: =MID(TRIM(A8),5,3) -> 100 | J8: =SUBSTITUTE(TRIM(A8),"-","/") -> ord/1005 | K8: =FIND("-",TRIM(A8)) -> 4 | L8: =UPPER(TRIM(A8)) -> ORD-1005 | M8: =Data!C6&" – "&Data!D6 -> Neha Trivedi – East
A10: Why TRIM first? Hidden leading/trailing spaces make 'ORD-1001 ' ≠ 'ORD-1001', so lookups fail. Clean, then look up.
A11: CONCATENATE(a,b) works the same as a&b; & is shorter and preferred.

Sheet Edge_Cases
A1: Edge-Case Tests
A3: # | B3: Scenario | C3: Test input | D3: Naive formula | E3: Naive result | F3: Robust formula | G3: Robust result | I3: Helper cells
A4: 1 | B4: Blank cell used in IF | C4: I4 (blank) | D4: =IF(I4>0,"Positive","Zero/Blank") | E4: =IF(I4>0,"Positive","Zero/Blank") -> Zero/Blank | F4: =IF(ISBLANK(I4),"Blank – skipped",IF(I4>0,"Positive","Zero")) | G4: =IF(ISBLANK(I4),"Blank – skipped",IF(I4>0,"Positive","Zero")) -> Blank – skipped | J4: I4 = truly blank
A5: 2 | B5: Number stored as text in SUM | C5: I5 ('25' text) | D5: =SUM(I5,I6) | E5: =SUM(I5,I6) -> 25 | F5: =SUM(VALUE(I5),I6) | G5: =SUM(VALUE(I5),I6) -> 50 | I5: 25 | J5: I5 = '25' stored as TEXT
A6: 3 | B6: Text vs number compare | C6: I5 vs I6 | D6: =I5=I6 | E6: =I5=I6 -> FALSE | F6: =VALUE(I5)=I6 | G6: =VALUE(I5)=I6 -> TRUE | I6: 25 | J6: I6 = number 25
A7: 4 | B7: Trailing space breaks lookup | C7: I7 ('P203 ') | D7: =VLOOKUP(I7,ProdTable,2,FALSE) | E7: =IFERROR(VLOOKUP(I7,ProdTable,2,FALSE()),"Lookup error caught") -> Lookup error caught | F7: =VLOOKUP(TRIM(I7),ProdTable,2,FALSE) | G7: =VLOOKUP(TRIM(I7),ProdTable,2,FALSE()) -> Mechanical Keyboard | I7: P203 | J7: I7 = 'P203 ' with trailing space
A8: 5 | B8: Missing key in lookup | C8: 'P999' | D8: =VLOOKUP("P999",ProdTable,2,FALSE) | E8: =IFERROR(VLOOKUP("P999",ProdTable,2,FALSE()),"Lookup error caught") -> Lookup error caught | F8: =IFERROR(VLOOKUP("P999",ProdTable,2,FALSE),"Not in product list") | G8: =IFERROR(VLOOKUP("P999",ProdTable,2,FALSE()),"Not in product list") -> Not in product list | I8: P203 | J8: I8 = 'P203'
A9: 6 | B9: Divide by zero (avg of empty group) | C9: 0 orders | D9: =0/0 | E9: =IFERROR(0/0,"Divide error caught") -> Divide error caught | F9: =IFERROR(0/0,0) | G9: =IFERROR(0/0,0) -> 0
A10: 7 | B10: COUNTIF ignores blanks vs COUNTA | C10: range I4:I8 | D10: =COUNTA(I4:I8) | E10: =COUNTA(I4:I8) -> 4 | F10: =COUNT(I4:I8) | G10: =COUNT(I4:I8) -> 1
A13: Naive formulas that would return an Excel error are shown wrapped in IFERROR here so the workbook stays error-free; in real use they would display the error.

Sheet Formula_Notes
A1: When to use each formula
A3: Formula | B3: Use it when… | C3: Watch out for
A4: VLOOKUP | B4: Pulling a value from a table when the key is in the LEFTMOST column | C4: Use FALSE for exact match; breaks if columns are inserted (hard-coded col index)
A5: XLOOKUP | B5: Modern replacement: any direction lookup, built-in 'not found' value, exact match by default | C5: Only Excel 365/2021+ and Google Sheets – not older Excel
A6: INDEX/MATCH | B6: Need to look left, or want lookups that survive column insertion; works in all versions | C6: Two functions – a bit longer; use 0 in MATCH for exact
A7: IF | B7: Two outcomes: pass/fail, high/low, flag/no flag | C7: Keep nested IFs to 3 levels – then use a lookup table
A8: IF + AND / OR | B8: Multiple conditions must all (AND) or any (OR) be true | C8: Remember to quote text criteria
A9: IFERROR | B9: Replace Excel errors (not-found, divide-by-zero) with a friendly message | C9: Don't use it to hide real bugs – test first
A10: SUMIF / SUMIFS | B10: Add values that meet 1 (SUMIF) or many (SUMIFS) conditions | C10: SUMIFS puts sum_range FIRST; SUMIF puts it LAST
A11: COUNTIF / COUNTIFS | B11: Count rows that meet one / several conditions | C11: Criteria like ">5" need quotes; use & to join cell references
A12: AVERAGEIFS | B12: Average of rows meeting conditions | C12: Wrap in IFERROR – no matching rows causes a divide-by-zero error
A13: LEFT / RIGHT / MID | B13: Extract fixed-position pieces (codes, years, prefixes) | C13: Combine with FIND to extract variable-length text
A14: TRIM / UPPER / LOWER / PROPER | B14: Clean messy imported text before lookups or grouping | C14: TRIM removes extra spaces but not non-breaking spaces (CHAR(160))
... A16: SUBSTITUTE | B16: Replace a specific character/word inside text | C16: Case-sensitive
A19: Interview questions – answers
A20: What's the difference between SUMIF and SUMIFS? | B20: SUMIF handles ONE condition; SUMIFS handles MANY (AND logic). Argument order differs: SUMIF(range, criteria, sum_range) vs SUMIFS(sum_range, range1, criteria1, range2, criteria2…). Prefer SUMIFS everywhere – it also works with a single condition.
A21: How does XLOOKUP improve on VLOOKUP? | B21: XLOOKUP looks in any direction (not only right), defaults to exact match, has a built-in if_not_found argument, uses a lookup column instead of a fragile column number, returns whole rows/columns, and can search last-to-first.
A22: When would you use INDEX/MATCH instead of VLOOKUP? | B22: When the lookup column is to the RIGHT of the return column, when columns may be inserted/deleted (no hard-coded index), on older Excel without XLOOKUP, or for two-way lookups with two MATCH functions and faster performance on big sheets.
